pip_requ/__init__.py
pip_requ/cache.py
pip_requ/click.py
pip_requ/exceptions.py
pip_requ/io.py
pip_requ/locations.py
pip_requ/logging.py
pip_requ/resolver.py
pip_requ/sync.py
pip_requ/utils.py
pip_requ/writer.py
pip_requ/_compat/__init__.py
pip_requ/_compat/contextlib.py
pip_requ/_compat/tempfile.py
pip_requ/repositories/__init__.py
pip_requ/repositories/base.py
pip_requ/repositories/local.py
pip_requ/repositories/pypi.py
pip_requ/scripts/__init__.py
pip_requ/scripts/_utils.py
pip_requ/scripts/build_wheels.py
pip_requ/scripts/compile.py
pip_requ/scripts/compile_all.py
pip_requ/scripts/pip_requ.py
pip_requ/scripts/sync.py
pip_requ/scripts/update.py
pip_requ-0.180.7.dist-info/DESCRIPTION.rst
pip_requ-0.180.7.dist-info/METADATA
pip_requ-0.180.7.dist-info/RECORD
pip_requ-0.180.7.dist-info/WHEEL
pip_requ-0.180.7.dist-info/entry_points.txt
pip_requ-0.180.7.dist-info/metadata.json
pip_requ-0.180.7.dist-info/top_level.txt
