Metadata-Version: 2.0
Name: pip-requ
Version: 0.180.7
Summary: Pip Requ helps managing your Python requirements files.
Home-page: https://github.com/suutari-ai/pip-requ/
Author: Tuomas Suutari
Author-email: tuomas.suutari@anders.fi
License: BSD
Platform: any
Classifier: Development Status :: 5 - Production/Stable
Classifier: Programming Language :: Python
Classifier: Programming Language :: Python :: 2
Classifier: Programming Language :: Python :: 2.7
Classifier: Programming Language :: Python :: 3
Classifier: Programming Language :: Python :: 3.4
Classifier: Programming Language :: Python :: 3.5
Classifier: Intended Audience :: Developers
Classifier: Intended Audience :: System Administrators
Classifier: License :: OSI Approved :: BSD License
Classifier: Operating System :: OS Independent
Classifier: Topic :: System :: Systems Administration
Requires-Dist: click (>=6)
Requires-Dist: first
Requires-Dist: six
